{
	"class" : {
		"bpExamplePragmaPrefix" : "ek 2/9/2021 14:39",
		"pragmaSelectors" : "ek 2/9/2021 15:47" },
	"instance" : {
		"asPragma" : "ek 2/9/2021 17:05",
		"browseMethod" : "ek 2/10/2021 11:19",
		"initializeFromPragma:" : "ek 2/9/2021 17:05",
		"methodSelector" : "ek 2/9/2021 14:55",
		"methodSelector:" : "ek 2/9/2021 15:15",
		"morphClass" : "ek 2/9/2021 15:36",
		"run" : "ek 2/16/2021 11:35",
		"testCaseClass" : "ek 2/9/2021 14:55",
		"testCaseClass:" : "ek 2/9/2021 15:15",
		"testCaseClassFrom:" : "ek 2/9/2021 15:42",
		"testCaseInstance" : "ek 2/9/2021 15:14",
		"testCaseInstance:" : "ek 2/9/2021 15:15" } }
