{
	"class" : {
		"fontHeight" : "pre 11/18/2019 10:40",
		"fontWidth" : "pre 11/18/2019 10:44" },
	"instance" : {
		"annotation" : "pre 7/2/2019 16:39",
		"annotation:" : "pre 7/2/2019 16:39",
		"codeContentChanged" : "pre 11/11/2019 10:25",
		"containingBrowser" : "pre 7/24/2019 16:42",
		"createErrorIndicatorFor:" : "pre 8/17/2020 09:17",
		"editFieldFor:text:onChange:onAccept:" : "pre 11/11/2019 10:06",
		"editFieldInitialContent:onChange:onAccept:" : "pre 11/11/2019 10:41",
		"emptyTraces" : "pre 8/6/2019 14:14",
		"ensureErrorIndicatorFor:" : "pre 8/17/2020 09:17",
		"ensureNoErrorIndicator" : "pre 8/17/2020 09:17",
		"errorIndicatorClicked:" : "pre 8/17/2020 09:17",
		"fontHeight" : "pre 11/18/2019 10:40",
		"fontWidth" : "pre 11/18/2019 10:43",
		"getErrorIndicator" : "pre 8/17/2020 09:17",
		"getTraces" : "pre 1/24/2020 14:28",
		"iconSize" : "pre 7/24/2019 13:18",
		"id" : "pre 7/2/2019 16:38",
		"id:" : "pre 7/2/2019 16:38",
		"initialize" : "pre 3/19/2020 14:00",
		"isAssertion" : "pre 7/3/2019 11:11",
		"isBPAnnotationMorph" : "pre 7/3/2019 11:10",
		"isExample" : "pre 7/23/2019 12:47",
		"isProbe" : "pre 7/3/2019 11:11",
		"isReplacement" : "pre 7/3/2019 11:11",
		"isSlider" : "pre 1/24/2020 16:15",
		"methodReference" : "pre 11/18/2019 12:28",
		"methodReference:" : "pre 11/18/2019 12:28",
		"newRemoveButton" : "pre 11/18/2019 12:30",
		"removeButtonClicked" : "pre 11/18/2019 12:29",
		"scrollBarSize" : "pre 7/23/2019 11:18",
		"startTag" : "pre 7/25/2019 15:42",
		"stopTag" : "pre 7/25/2019 15:42",
		"textEmphasis" : "pre 11/14/2019 14:29" } }
